tests/__init__.py
tests/conftest.py
tests/test_download.py
tests/test_parameters.py
tests/test_performance.py
tests/test_rank.py
tests/test_top.py
tranco/__init__.py
tranco/tranco.py
tranco-0.8.1.dist-info/LICENSE
tranco-0.8.1.dist-info/METADATA
tranco-0.8.1.dist-info/WHEEL
tranco-0.8.1.dist-info/top_level.txt
tranco-0.8.1.dist-info/RECORD
