Metadata-Version: 2.1
Name: tranco
Version: 0.8.1
Summary: Tranco: A Research-Oriented Top Sites Ranking Hardened Against Manipulation
Home-page: https://github.com/DistriNet/tranco-python-package
Author: Victor Le Pochat
Author-email: victor.lepochat@kuleuven.be
Classifier: Programming Language :: Python :: 3
Classifier: License :: OSI Approved :: MIT License
Classifier: Operating System :: OS Independent
License-File: LICENSE
Requires-Dist: requests
Provides-Extra: dev
Requires-Dist: pytest; extra == "dev"
Requires-Dist: codetiming; extra == "dev"
